MinProxy/__init__.py
MinProxy-1.0.0.dist-info/LICENSE
MinProxy-1.0.0.dist-info/METADATA
MinProxy-1.0.0.dist-info/WHEEL
MinProxy-1.0.0.dist-info/top_level.txt
MinProxy-1.0.0.dist-info/RECORD
