Metadata-Version: 2.1
Name: MinProxy
Version: 1.0.0
Summary: Get Proxy Python
Home-page: UNKNOWN
Author: Lê Tuấn Tài
Author-email: taile.official06@gmail.com
License: UNKNOWN
Keywords: proxy in python,python proxy,minproxu,pip install proxy,pip install minproxy
Platform: UNKNOWN
Classifier: Development Status :: 1 - Planning
Classifier: Intended Audience :: Developers
Classifier: Programming Language :: Python :: 3
Classifier: Operating System :: Unix
Classifier: Operating System :: MacOS :: MacOS X
Classifier: Operating System :: Microsoft :: Windows
License-File: LICENSE
Requires-Dist: requests
